plume/__init__.py
plume/decoder/__init__.py
plume/decoder/frame/__init__.py
plume/decoder/frame/component/__init__.py
plume/decoder/frame/component/camera_decoder.py
plume/decoder/frame/component/mesh_filter_decoder.py
plume/decoder/frame/component/mesh_renderer_decoder.py
plume/decoder/frame/component/transform_decoder.py
plume/decoder/frame/component/xr_base_interactable_decoder.py
plume/decoder/frame/component/xr_base_interactor_decoder.py
plume/decoder/frame/frame_data_decoder.py
plume/decoder/frame/frame_data_decoder_registry.py
plume/decoder/frame/frame_decoder.py
plume/decoder/frame/game_object_decoder.py
plume/decoder/frame/xritk_interaction_decoder.py
plume/decoder/input_action_decoder.py
plume/decoder/lsl_stream_decoder.py
plume/decoder/marker_decoder.py
plume/decoder/record_metadata_decoder.py
plume/decoder/record_reader.py
plume/decoder/sample_stream_reader.py
plume/export/__init__.py
plume/export/xdf_exporter.py
plume/export/xdf_writer.py
plume/proxy/__init__.py
plume/proxy/collection.py
plume/proxy/common/__init__.py
plume/proxy/common/animation_curve.py
plume/proxy/common/bounds.py
plume/proxy/common/color.py
plume/proxy/common/marker.py
plume/proxy/common/matrix4x4.py
plume/proxy/common/quaternion.py
plume/proxy/common/rect.py
plume/proxy/common/spherical_harmonics.py
plume/proxy/common/vector2.py
plume/proxy/common/vector3.py
plume/proxy/common/vector4.py
plume/proxy/lsl/__init__.py
plume/proxy/lsl/stream.py
plume/proxy/record_metadata.py
plume/proxy/unity/__init__.py
plume/proxy/unity/asset.py
plume/proxy/unity/asset_collection.py
plume/proxy/unity/component/__init__.py
plume/proxy/unity/component/camera.py
plume/proxy/unity/component/component.py
plume/proxy/unity/component/component_collection.py
plume/proxy/unity/component/mesh_filter.py
plume/proxy/unity/component/mesh_renderer.py
plume/proxy/unity/component/renderer.py
plume/proxy/unity/component/transform.py
plume/proxy/unity/component/xr_base_interactable.py
plume_python-1.3.2.dist-info/LICENSE
plume_python-1.3.2.dist-info/METADATA
plume_python-1.3.2.dist-info/WHEEL
plume_python-1.3.2.dist-info/RECORD
