Metadata-Version: 2.3
Name: plume-python
Version: 1.3.2
Summary: Set of utilities to work with PLM record files.
License: GPLv3
Author: Charles JAVERLIAT
Author-email: charles.javerliat@gmail.com
Requires-Python: >=3.10,<4.0
Classifier: License :: Other/Proprietary License
Classifier: Programming Language :: Python :: 3
Classifier: Programming Language :: Python :: 3.10
Classifier: Programming Language :: Python :: 3.11
Classifier: Programming Language :: Python :: 3.12
Classifier: Programming Language :: Python :: 3.13
Requires-Dist: betterproto (>=1.2.5,<2.0.0)
Requires-Dist: click (>=8.0.3,<9.0.0)
Requires-Dist: delimited-protobuf (>=1.0.0,<2.0.0)
Requires-Dist: lz4 (>=4.3.2,<5.0.0)
Requires-Dist: numpy (>=1.21.0,<2.0.0)
Requires-Dist: pandas (>=2.2.2,<3.0.0)
Requires-Dist: protobuf (>=5.29.3,<6.0.0)
Requires-Dist: tqdm (>=4.66.4,<5.0.0)
Requires-Dist: typing-extensions (>=4.12.2,<5.0.0)
Project-URL: Repository, https://github.com/liris-xr/PLUME-Python
